waitress-stubs/METADATA.toml
waitress-stubs/__init__.pyi
waitress-stubs/adjustments.pyi
waitress-stubs/buffers.pyi
waitress-stubs/channel.pyi
waitress-stubs/compat.pyi
waitress-stubs/parser.pyi
waitress-stubs/proxy_headers.pyi
waitress-stubs/py.typed
waitress-stubs/receiver.pyi
waitress-stubs/rfc7230.pyi
waitress-stubs/runner.pyi
waitress-stubs/server.pyi
waitress-stubs/task.pyi
waitress-stubs/trigger.pyi
waitress-stubs/utilities.pyi
waitress-stubs/wasyncore.pyi
types_waitress-3.0.1.20241117.dist-info/METADATA
types_waitress-3.0.1.20241117.dist-info/WHEEL
types_waitress-3.0.1.20241117.dist-info/top_level.txt
types_waitress-3.0.1.20241117.dist-info/RECORD
